kpireport/__init__.py
kpireport/__main__.py
kpireport/cmd.py
kpireport/config.py
kpireport/datasource.py
kpireport/license.py
kpireport/output.py
kpireport/plugin.py
kpireport/report.py
kpireport/utils.py
kpireport/version.py
kpireport/view.py
kpireport/license_keys/2020-12.pub
kpireport/templates/view.html
kpireport/templates/view.md
kpireport/templates/layout/default.html
kpireport/templates/layout/default.md
kpireport/templates/layout/styles.html
kpireport-0.1.8.dist-info/LICENSE.md
kpireport-0.1.8.dist-info/METADATA
kpireport-0.1.8.dist-info/WHEEL
kpireport-0.1.8.dist-info/entry_points.txt
kpireport-0.1.8.dist-info/top_level.txt
kpireport-0.1.8.dist-info/RECORD
