Metadata-Version: 2.1
Name: kpireport
Version: 0.1.8
Summary: KPI Report generator
Home-page: UNKNOWN
License: Prosperity Public License
Keywords: kpi,mail,report,devops
Platform: UNKNOWN
Classifier: Development Status :: 4 - Beta
Classifier: Intended Audience :: Developers
Classifier: Intended Audience :: System Administrators
Classifier: License :: Other/Proprietary License
Classifier: Programming Language :: Python :: 3
Classifier: Topic :: Software Development
Classifier: Topic :: System :: Monitoring
Requires-Python: ~=3.3
Requires-Dist: authlib
Requires-Dist: jinja2
Requires-Dist: pandas
Requires-Dist: python-dateutil
Requires-Dist: python-slugify
Requires-Dist: pyyaml
Requires-Dist: stevedore
Provides-Extra: all
Requires-Dist: kpireport-googleanalytics ; extra == 'all'
Requires-Dist: kpireport-jenkins ; extra == 'all'
Requires-Dist: kpireport-mysql ; extra == 'all'
Requires-Dist: kpireport-plot ; extra == 'all'
Requires-Dist: kpireport-prometheus ; extra == 'all'
Requires-Dist: kpireport-s3 ; extra == 'all'
Requires-Dist: kpireport-scp ; extra == 'all'
Requires-Dist: kpireport-sendgrid ; extra == 'all'
Requires-Dist: kpireport-slack ; extra == 'all'
Requires-Dist: kpireport-smtp ; extra == 'all'
Requires-Dist: kpireport-static ; extra == 'all'
Requires-Dist: kpireport-table ; extra == 'all'
Requires-Dist: kpireport-twitter ; extra == 'all'
